astrostash/__init__.py
astrostash/astrostash.py
astrostash/heasarc/__init__.py
astrostash/heasarc/core.py
astrostash/heasarc/tests/__init__.py
astrostash/heasarc/tests/test_heasarc.py
astrostash/heasarc/tests/data/processed-conflict.db
astrostash/schema/base.sql
astrostash/tests/__init__.py
astrostash/tests/test_astrostash_core.py
astrostash-0.1.1.dist-info/licenses/LICENSE
astrostash-0.1.1.dist-info/METADATA
astrostash-0.1.1.dist-info/WHEEL
astrostash-0.1.1.dist-info/top_level.txt
astrostash-0.1.1.dist-info/RECORD
