Metadata-Version: 2.4
Name: astrostash
Version: 0.1.1
Summary: An astronomy/astrophysics database building and syncing library
Author-email: Nicholas Kuechel <njkuechel@protonmail.com>
License-Expression: BSD-3-Clause
Requires-Python: >=3.10
License-File: LICENSE
Requires-Dist: astroquery>=0.4.10
Requires-Dist: pandas>=2.3.0
Requires-Dist: SQLAlchemy>=2.0.43
Provides-Extra: dev
Requires-Dist: build>=0.10.0; extra == "dev"
Requires-Dist: pytest>=8.4.1; extra == "dev"
Requires-Dist: pytest-cov>=6.2.1; extra == "dev"
Requires-Dist: flake8>=7.3.0; extra == "dev"
Dynamic: license-file
